mediadecoder/__init__.py
mediadecoder/decoder.py
mediadecoder/states.py
mediadecoder/timer.py
mediadecoder/soundrenderers/__init__.py
mediadecoder/soundrenderers/_base.py
mediadecoder/soundrenderers/pyaudiorenderer.py
mediadecoder/soundrenderers/pyaudiorenderer2.py
mediadecoder/soundrenderers/pygamerenderer.py
mediadecoder/soundrenderers/sounddevicerenderer.py
mediadecoder/soundrenderers/sounddevicerenderer2.py
mediadecoder-0.2.3.dist-info/licenses/copyright
mediadecoder-0.2.3.dist-info/WHEEL
mediadecoder-0.2.3.dist-info/METADATA
mediadecoder-0.2.3.dist-info/RECORD
