Metadata-Version: 2.4
Name: mediadecoder
Version: 0.2.3
Summary: Media-decoding library based on MoviePy
Keywords: media,movie,playback
Author-email: Daniel Schreij <dschreij@gmail.com>, Sebastiaan Mathôt <s.mathot@cogsci.nl>
Requires-Python: >=3.10
License-File: copyright
Requires-Dist: moviepy
Requires-Dist: numpy
Project-URL: Source, https://github.com/open-cogsci/python-mediadecoder
